Workbook

Sheet Summary
A1: MAJLAS FLOOD PROTECTION — COST-BENEFIT SUMMARY
A3: Metric | B3: Value
A4: Annual avoided damage (OMR/yr) | B4: =Damage_AED!$B$17
A5: AED baseline (OMR/yr) | B5: =Damage_AED!$B$15
A6: AED scheme (OMR/yr) | B6: =Damage_AED!$B$16
A7: Initial cost (OMR) | B7: =NPV_BCR!B55
A8: PV benefits (OMR) | B8: =NPV_BCR!B56
A9: PV costs (OMR) | B9: =NPV_BCR!B58
A10: NPV (OMR) | B10: =NPV_BCR!B59
A11: BCR | B11: =NPV_BCR!B60
A12: EAPE avoided (people/yr) | B12: =Exposure!$B$17
A14: Verdict: | B14: =IF(B11>1,"Viable (BCR>1)","Not viable on damage alone - see life-safety metrics")

Sheet Inputs
A1: MAJLAS FLOOD PROTECTION — COST-BENEFIT INPUTS
A3: Parameter | B3: Value | C3: Unit
A4: Dam capital cost | B4: 50000000 | C4: OMR
A5: Channel capital cost | B5: 5000000 | C5: OMR
A6: Relocation cost | B6: 168080 | C6: OMR
A7: Discount rate (r) | B7: 0.025 | C7: fraction
A8: Horizon (n) | B8: 50 | C8: years
A9: Dam maintenance rate | B9: 0.01 | C9: of dam capital / yr
A10: Dam maintenance start | B10: 5 | C10: year
A11: Channel maintenance rate | B11: 0.007 | C11: of channel capital / yr
A12: Channel maintenance start | B12: 2 | C12: year
A14: ↑ yellow cells are editable — results update automatically

Sheet Damage_AED
A1: Flood damage by return period (from GIS pipeline)
A3: Return period (yr) | B3: Exceedance prob | C3: Damage baseline (OMR) | D3: Damage scheme (OMR) | E3: Trapezoid baseline | F3: Trapezoid scheme
A4: 2 | B4: =1/A4 | C4: 430603 | D4: 413027 | E4: =0.5*(C4+C5)*(B4-B5) | F4: =0.5*(D4+D5)*(B4-B5)
A5: 5 | B5: =1/A5 | C5: 1011369 | D5: 667876 | E5: =0.5*(C5+C6)*(B5-B6) | F5: =0.5*(D5+D6)*(B5-B6)
A6: 10 | B6: =1/A6 | C6: 2286454 | D6: 1105001 | E6: =0.5*(C6+C7)*(B6-B7) | F6: =0.5*(D6+D7)*(B6-B7)
A7: 25 | B7: =1/A7 | C7: 3513744 | D7: 1352664 | E7: =0.5*(C7+C8)*(B7-B8) | F7: =0.5*(D7+D8)*(B7-B8)
A8: 50 | B8: =1/A8 | C8: 4670209 | D8: 1576424 | E8: =0.5*(C8+C9)*(B8-B9) | F8: =0.5*(D8+D9)*(B8-B9)
A9: 100 | B9: =1/A9 | C9: 5900757 | D9: 1818152 | E9: =0.5*(C9+C10)*(B9-B10) | F9: =0.5*(D9+D10)*(B9-B10)
A10: 200 | B10: =1/A10 | C10: 7456451 | D10: 2093806 | E10: =0.5*(C10+C11)*(B10-B11) | F10: =0.5*(D10+D11)*(B10-B11)
A11: 500 | B11: =1/A11 | C11: 9499861 | D11: 2813500 | E11: =0.5*(C11+C12)*(B11-B12) | F11: =0.5*(D11+D12)*(B11-B12)
A12: 1000 | B12: =1/A12 | C12: 11019644 | D12: 3789619 | E12: =0.5*(C12+C13)*(B12-B13) | F12: =0.5*(D12+D13)*(B12-B13)
A13: 10000 | B13: =1/A13 | C13: 14243470 | D13: 8922389
A15: AED baseline (OMR/yr) | B15: =SUM(E4:E12)+C13*B13
A16: AED scheme (OMR/yr) | B16: =SUM(F4:F12)+D13*B13
A17: Annual avoided damage (OMR/yr) | B17: =B15-B16

Sheet NPV_BCR
A1: Discounted cash flow (formula-driven)
A3: Year | B3: Avoided damage | C3: Dam maint. | D3: Channel maint. | E3: Net benefit | F3: Discount factor | G3: PV net | H3: PV benefit | I3: PV cost
A4: 1 | B4: =Damage_AED!$B$17 | C4: =IF(A4>=Inputs!$B$10,Inputs!$B$9*Inputs!$B$4,0) | D4: =IF(A4>=Inputs!$B$12,Inputs!$B$11*Inputs!$B$5,0) | E4: =B4-C4-D4 | F4: =1/(1+Inputs!$B$7)^A4 | G4: =E4*F4 | H4: =B4*F4 | I4: =(C4+D4)*F4
A5: 2 | B5: =Damage_AED!$B$17 | C5: =IF(A5>=Inputs!$B$10,Inputs!$B$9*Inputs!$B$4,0) | D5: =IF(A5>=Inputs!$B$12,Inputs!$B$11*Inputs!$B$5,0) | E5: =B5-C5-D5 | F5: =1/(1+Inputs!$B$7)^A5 | G5: =E5*F5 | H5: =B5*F5 | I5: =(C5+D5)*F5
A6: 3 | B6: =Damage_AED!$B$17 | C6: =IF(A6>=Inputs!$B$10,Inputs!$B$9*Inputs!$B$4,0) | D6: =IF(A6>=Inputs!$B$12,Inputs!$B$11*Inputs!$B$5,0) | E6: =B6-C6-D6 | F6: =1/(1+Inputs!$B$7)^A6 | G6: =E6*F6 | H6: =B6*F6 | I6: =(C6+D6)*F6
A7: 4 | B7: =Damage_AED!$B$17 | C7: =IF(A7>=Inputs!$B$10,Inputs!$B$9*Inputs!$B$4,0) | D7: =IF(A7>=Inputs!$B$12,Inputs!$B$11*Inputs!$B$5,0) | E7: =B7-C7-D7 | F7: =1/(1+Inputs!$B$7)^A7 | G7: =E7*F7 | H7: =B7*F7 | I7: =(C7+D7)*F7
A8: 5 | B8: =Damage_AED!$B$17 | C8: =IF(A8>=Inputs!$B$10,Inputs!$B$9*Inputs!$B$4,0) | D8: =IF(A8>=Inputs!$B$12,Inputs!$B$11*Inputs!$B$5,0) | E8: =B8-C8-D8 | F8: =1/(1+Inputs!$B$7)^A8 | G8: =E8*F8 | H8: =B8*F8 | I8: =(C8+D8)*F8
A9: 6 | B9: =Damage_AED!$B$17 | C9: =IF(A9>=Inputs!$B$10,Inputs!$B$9*Inputs!$B$4,0) | D9: =IF(A9>=Inputs!$B$12,Inputs!$B$11*Inputs!$B$5,0) | E9: =B9-C9-D9 | F9: =1/(1+Inputs!$B$7)^A9 | G9: =E9*F9 | H9: =B9*F9 | I9: =(C9+D9)*F9
A10: 7 | B10: =Damage_AED!$B$17 | C10: =IF(A10>=Inputs!$B$10,Inputs!$B$9*Inputs!$B$4,0) | D10: =IF(A10>=Inputs!$B$12,Inputs!$B$11*Inputs!$B$5,0) | E10: =B10-C10-D10 | F10: =1/(1+Inputs!$B$7)^A10 | G10: =E10*F10 | H10: =B10*F10 | I10: =(C10+D10)*F10
A11: 8 | B11: =Damage_AED!$B$17 | C11: =IF(A11>=Inputs!$B$10,Inputs!$B$9*Inputs!$B$4,0) | D11: =IF(A11>=Inputs!$B$12,Inputs!$B$11*Inputs!$B$5,0) | E11: =B11-C11-D11 | F11: =1/(1+Inputs!$B$7)^A11 | G11: =E11*F11 | H11: =B11*F11 | I11: =(C11+D11)*F11
A12: 9 | B12: =Damage_AED!$B$17 | C12: =IF(A12>=Inputs!$B$10,Inputs!$B$9*Inputs!$B$4,0) | D12: =IF(A12>=Inputs!$B$12,Inputs!$B$11*Inputs!$B$5,0) | E12: =B12-C12-D12 | F12: =1/(1+Inputs!$B$7)^A12 | G12: =E12*F12 | H12: =B12*F12 | I12: =(C12+D12)*F12
A13: 10 | B13: =Damage_AED!$B$17 | C13: =IF(A13>=Inputs!$B$10,Inputs!$B$9*Inputs!$B$4,0) | D13: =IF(A13>=Inputs!$B$12,Inputs!$B$11*Inputs!$B$5,0) | E13: =B13-C13-D13 | F13: =1/(1+Inputs!$B$7)^A13 | G13: =E13*F13 | H13: =B13*F13 | I13: =(C13+D13)*F13
A14: 11 | B14: =Damage_AED!$B$17 | C14: =IF(A14>=Inputs!$B$10,Inputs!$B$9*Inputs!$B$4,0) | D14: =IF(A14>=Inputs!$B$12,Inputs!$B$11*Inputs!$B$5,0) | E14: =B14-C14-D14 | F14: =1/(1+Inputs!$B$7)^A14 | G14: =E14*F14 | H14: =B14*F14 | I14: =(C14+D14)*F14
A15: 12 | B15: =Damage_AED!$B$17 | C15: =IF(A15>=Inputs!$B$10,Inputs!$B$9*Inputs!$B$4,0) | D15: =IF(A15>=Inputs!$B$12,Inputs!$B$11*Inputs!$B$5,0) | E15: =B15-C15-D15 | F15: =1/(1+Inputs!$B$7)^A15 | G15: =E15*F15 | H15: =B15*F15 | I15: =(C15+D15)*F15
... A53: 50 | B53: =Damage_AED!$B$17 | C53: =IF(A53>=Inputs!$B$10,Inputs!$B$9*Inputs!$B$4,0) | D53: =IF(A53>=Inputs!$B$12,Inputs!$B$11*Inputs!$B$5,0) | E53: =B53-C53-D53 | F53: =1/(1+Inputs!$B$7)^A53 | G53: =E53*F53 | H53: =B53*F53 | I53: =(C53+D53)*F53
A55: Initial cost (dam+channel+relocation) | B55: =Inputs!$B$4+Inputs!$B$5+Inputs!$B$6
A56: PV of benefits (avoided damage) | B56: =SUM(H4:H53)
A57: PV of maintenance | B57: =SUM(I4:I53)
A58: PV of costs (initial + maintenance) | B58: =B55+B57
A59: NPV | B59: =B56-B57-B55
A60: BCR | B60: =B56/B58

Sheet Exposure
A1: Population exposure by return period
A3: Return period (yr) | B3: Prob | C3: People exposed base | D3: People exposed scheme | E3: >1 m base (life-risk) | F3: >1 m scheme | G3: Trap base | H3: Trap scheme
A4: 2 | B4: =1/A4 | C4: 1796 | D4: 1085 | E4: 158 | F4: 84 | G4: =0.5*(C4+C5)*(B4-B5) | H4: =0.5*(D4+D5)*(B4-B5)
A5: 5 | B5: =1/A5 | C5: 3147 | D5: 1629 | E5: 524 | F5: 132 | G5: =0.5*(C5+C6)*(B5-B6) | H5: =0.5*(D5+D6)*(B5-B6)
A6: 10 | B6: =1/A6 | C6: 4527 | D6: 2155 | E6: 1335 | F6: 205 | G6: =0.5*(C6+C7)*(B6-B7) | H6: =0.5*(D6+D7)*(B6-B7)
A7: 25 | B7: =1/A7 | C7: 5356 | D7: 2438 | E7: 2110 | F7: 258 | G7: =0.5*(C7+C8)*(B7-B8) | H7: =0.5*(D7+D8)*(B7-B8)
A8: 50 | B8: =1/A8 | C8: 5862 | D8: 2699 | E8: 2813 | F8: 312 | G8: =0.5*(C8+C9)*(B8-B9) | H8: =0.5*(D8+D9)*(B8-B9)
A9: 100 | B9: =1/A9 | C9: 6207 | D9: 2978 | E9: 3564 | F9: 374 | G9: =0.5*(C9+C10)*(B9-B10) | H9: =0.5*(D9+D10)*(B9-B10)
A10: 200 | B10: =1/A10 | C10: 6432 | D10: 3253 | E10: 4334 | F10: 447 | G10: =0.5*(C10+C11)*(B10-B11) | H10: =0.5*(D10+D11)*(B10-B11)
A11: 500 | B11: =1/A11 | C11: 6617 | D11: 3831 | E11: 5259 | F11: 783 | G11: =0.5*(C11+C12)*(B11-B12) | H11: =0.5*(D11+D12)*(B11-B12)
A12: 1000 | B12: =1/A12 | C12: 6724 | D12: 4305 | E12: 5790 | F12: 1531 | G12: =0.5*(C12+C13)*(B12-B13) | H12: =0.5*(D12+D13)*(B12-B13)
A13: 10000 | B13: =1/A13 | C13: 7012 | D13: 6489 | E13: 6334 | F13: 4394
A15: EAPE baseline (people/yr) | B15: =SUM(G4:G12)+C13*B13
A16: EAPE scheme (people/yr) | B16: =SUM(H4:H12)+D13*B13
A17: Annual people-exposure avoided | B17: =B15-B16
